src/alu_8bit.v
module alu_8bit (
    input [7:0] a,
    input [7:0] b,
    input [3:0] alu_op,
    output reg [7:0] result,
    output reg zero_flag,
    output reg carry_flag,
    output reg overflow_flag
);

    parameter ADD  = 4'b0000;
    parameter SUB  = 4'b0001;
    parameter AND  = 4'b0010;
    parameter OR   = 4'b0011;
    parameter XOR  = 4'b0100;
    parameter NOT  = 4'b0101;
    parameter SLL  = 4'b0110;
    parameter SRL  = 4'b0111;
    parameter SRA  = 4'b1000;
    parameter EQ   = 4'b1001;
    parameter LT   = 4'b1010;
    parameter GT   = 4'b1011;

    reg [8:0] temp;

    always @(*) begin
        carry_flag = 0;
        overflow_flag = 0;
        
        case(alu_op)
            ADD: begin
                temp = a + b;
                result = temp[7:0];
                carry_flag = temp[8];
                overflow_flag = (a[7] == b[7]) && (result[7] != a[7]);
            end
            
            SUB: begin
                temp = a - b;
                result = temp[7:0];
                carry_flag = temp[8];
                overflow_flag = (a[7] != b[7]) && (result[7] != a[7]);
            end
            
            AND: result = a & b;
            OR:  result = a | b;
            XOR: result = a ^ b;
            NOT: result = ~a;
            SLL: result = a << b[2:0];
            SRL: result = a >> b[2:0];
            SRA: result = $signed(a) >>> b[2:0];
            EQ:  result = (a == b) ? 8'b1 : 8'b0;
            LT:  result = (a < b) ? 8'b1 : 8'b0;
            GT:  result = (a > b) ? 8'b1 : 8'b0;
            
            default: result = 8'b0;
        endcase
        
        zero_flag = (result == 8'b0);
    end

endmodule

src/alu_8bit_tb.v
`timescale 1ns/1ps

module alu_8bit_tb;
    reg [7:0] a, b;
    reg [3:0] alu_op;
    wire [7:0] result;
    wire zero_flag, carry_flag, overflow_flag;
    
    alu_8bit uut (
        .a(a),
        .b(b),
        .alu_op(alu_op),
        .result(result),
        .zero_flag(zero_flag),
        .carry_flag(carry_flag),
        .overflow_flag(overflow_flag)
    );
    
    initial begin
        $dumpfile("alu_8bit_tb.vcd");
        $dumpvars(0, alu_8bit_tb);
        
        // Test ADD
        a = 8'd15; b = 8'd10; alu_op = 4'b0000; #10;
        $display("ADD: %d + %d = %d, Carry=%b", a, b, result, carry_flag);
        
        // Test SUB
        a = 8'd25; b = 8'd10; alu_op = 4'b0001; #10;
        $display("SUB: %d - %d = %d", a, b, result);
        
        // Test AND
        a = 8'b11110000; b = 8'b10101010; alu_op = 4'b0010; #10;
        $display("AND: %b & %b = %b", a, b, result);
        
        // Test OR
        a = 8'b11110000; b = 8'b10101010; alu_op = 4'b0011; #10;
        $display("OR: %b | %b = %b", a, b, result);
        
        // Test XOR
        a = 8'b11110000; b = 8'b10101010; alu_op = 4'b0100; #10;
        $display("XOR: %b ^ %b = %b", a, b, result);
        
        // Test NOT
        a = 8'b11110000; alu_op = 4'b0101; #10;
        $display("NOT: ~%b = %b", a, result);
        
        // Test SLL
        a = 8'd4; b = 8'd2; alu_op = 4'b0110; #10;
        $display("SLL: %d << %d = %d", a, b[2:0], result);
        
        // Test SRL
        a = 8'd16; b = 8'd2; alu_op = 4'b0111; #10;
        $display("SRL: %d >> %d = %d", a, b[2:0], result);
        
        // Test overflow (ADD)
        a = 8'd127; b = 8'd1; alu_op = 4'b0000; #10;
        $display("ADD Overflow: %d + %d = %d, Overflow=%b", a, b, result, overflow_flag);
        
        // Test carry (ADD)
        a = 8'd255; b = 8'd1; alu_op = 4'b0000; #10;
        $display("ADD Carry: %d + %d = %d, Carry=%b", a, b, result, carry_flag);
        
        // Test zero flag
        a = 8'd5; b = 8'd5; alu_op = 4'b0001; #10;
        $display("SUB Zero: %d - %d = %d, Zero=%b", a, b, result, zero_flag);
        
        // Test EQ
        a = 8'd42; b = 8'd42; alu_op = 4'b1001; #10;
        $display("EQ: %d == %d = %d", a, b, result);
        
        // Test LT
        a = 8'd10; b = 8'd20; alu_op = 4'b1010; #10;
        $display("LT: %d < %d = %d", a, b, result);
        
        // Test GT
        a = 8'd30; b = 8'd20; alu_op = 4'b1011; #10;
        $display("GT: %d > %d = %d", a, b, result);
        
        #10 $finish;
    end
endmodule

simulations/alu_8bit_tb.vcd
$date
	Thu Oct 30 23:22:40 2025
$end
$version
	Icarus Verilog
$end
$timescale
	1ps
$end
$scope module alu_8bit_tb $end
$var wire 1 ! zero_flag $end
$var wire 8 " result [7:0] $end
$var wire 1 # overflow_flag $end
$var wire 1 $ carry_flag $end
$var reg 8 % a [7:0] $end
$var reg 4 & alu_op [3:0] $end
$var reg 8 ' b [7:0] $end
$scope module uut $end
$var wire 8 ( a [7:0] $end
$var wire 4 ) alu_op [3:0] $end
$var wire 8 * b [7:0] $end
$var reg 1 $ carry_flag $end
$var reg 1 # overflow_flag $end
$var reg 8 + result [7:0] $end
$var reg 9 , temp [8:0] $end
$var reg 1 ! zero_flag $end
$upscope $end
$upscope $end
$enddefinitions $end
#0
$dumpvars
b11001 ,
b11001 +
b1010 *
b0 )
b1111 (
b1010 '
b0 &
b1111 %
0$
0#
b11001 "
0!
$end
#10000
b1111 "
b1111 +
b1111 ,
b1 &
b1 )
b11001 %
b11001 (
#20000
b10100000 "
b10100000 +
b10 &
b10 )
b10101010 '
b10101010 *
b11110000 %
b11110000 (
#30000
b11111010 "
b11111010 +
b11 &
b11 )
#40000
b1011010 "
b1011010 +
b100 &
b100 )
#50000
b1111 "
b1111 +
b101 &
b101 )
#60000
b10000 "
b10000 +
b110 &
b110 )
b10 '
b10 *
b100 %
b100 (
#70000
b100 "
b100 +
b111 &
b111 )
b10000 %
b10000 (
#80000
1#
b10000000 "
b10000000 +
b10000000 ,
b0 &
b0 )
b1 '
b1 *
b1111111 %
b1111111 (
#90000
1!
1$
b0 "
b0 +
b100000000 ,
0#
b11111111 %
b11111111 (
#100000
b0 ,
0$
b1 &
b1 )
b101 '
b101 *
b101 %
b101 (
#110000
0!
b1 "
b1 +
b1001 &
b1001 )
b101010 '
b101010 *
b101010 %
b101010 (
#120000
b1010 &
b1010 )
b10100 '
b10100 *
b1010 %
b1010 (
#130000
b1011 &
b1011 )
b11110 %
b11110 (
